README.md
setup.py
dynamof/__init__.py
dynamof/attribute.py
dynamof/db.py
dynamof/table.py
dynamof.egg-info/PKG-INFO
dynamof.egg-info/SOURCES.txt
dynamof.egg-info/dependency_links.txt
dynamof.egg-info/requires.txt
dynamof.egg-info/top_level.txt
dynamof/core/Immutable.py
dynamof/core/args.py
dynamof/core/builder.py
dynamof/core/dynamo.py
dynamof/core/exceptions.py
dynamof/core/executor.py
dynamof/core/model.py
dynamof/core/response.py
dynamof/core/utils.py
dynamof/operations/add.py
dynamof/operations/create.py
dynamof/operations/delete.py
dynamof/operations/describe.py
dynamof/operations/find.py
dynamof/operations/query.py
dynamof/operations/scan.py
dynamof/operations/update.py